audiometa/__init__.py
audiometa/__main__.py
audiometa/_audio_file.py
audiometa/cli.py
audiometa/exceptions.py
audiometa/manager/_MetadataManager.py
audiometa/manager/__init__.py
audiometa/manager/_rating_supporting/_RatingSupportingMetadataManager.py
audiometa/manager/_rating_supporting/__init__.py
audiometa/manager/_rating_supporting/id3v2/_Id3v2Manager.py
audiometa/manager/_rating_supporting/id3v2/__init__.py
audiometa/manager/_rating_supporting/id3v2/_id3v2_constants.py
audiometa/manager/_rating_supporting/riff/_RiffManager.py
audiometa/manager/_rating_supporting/riff/__init__.py
audiometa/manager/_rating_supporting/riff/_riff_bext_chunk.py
audiometa/manager/_rating_supporting/riff/_riff_constants.py
audiometa/manager/_rating_supporting/riff/_riff_file_structure.py
audiometa/manager/_rating_supporting/riff/_riff_info_chunk.py
audiometa/manager/_rating_supporting/vorbis/_VorbisManager.py
audiometa/manager/_rating_supporting/vorbis/__init__.py
audiometa/manager/_rating_supporting/vorbis/_vorbis_constants.py
audiometa/manager/id3v1/_Id3v1Manager.py
audiometa/manager/id3v1/__init__.py
audiometa/manager/id3v1/_constants.py
audiometa/manager/id3v1/id3v1_raw_metadata.py
audiometa/manager/id3v1/id3v1_raw_metadata_key.py
audiometa/test/__init__.py
audiometa/test/assets/create_test_files.py
audiometa/test/helpers/__init__.py
audiometa/test/helpers/technical_info_inspector.py
audiometa/test/helpers/temp_file_with_metadata.py
audiometa/test/helpers/common/__init__.py
audiometa/test/helpers/common/audio_file_creator.py
audiometa/test/helpers/common/external_tool_runner.py
audiometa/test/helpers/id3v1/__init__.py
audiometa/test/helpers/id3v1/id3v1_header_verifier.py
audiometa/test/helpers/id3v1/id3v1_metadata_deleter.py
audiometa/test/helpers/id3v1/id3v1_metadata_getter.py
audiometa/test/helpers/id3v1/id3v1_metadata_setter.py
audiometa/test/helpers/id3v2/__init__.py
audiometa/test/helpers/id3v2/id3v2_frame_manual_creator.py
audiometa_python-0.11.1.dist-info/licenses/LICENSE
audiometa_python-0.11.1.dist-info/METADATA
audiometa_python-0.11.1.dist-info/WHEEL
audiometa_python-0.11.1.dist-info/entry_points.txt
audiometa_python-0.11.1.dist-info/top_level.txt
audiometa_python-0.11.1.dist-info/RECORD
