Metadata-Version: 2.4
Name: audiometa-python
Version: 0.11.1
Summary: A comprehensive Python library for reading and writing audio metadata across multiple formats
Author: AudioMeta Python Contributors
Author-email: Andreas Garcia <garcia.andreas.1991@gmail.com>
License: Apache-2.0
Project-URL: Homepage, https://github.com/your-username/audiometa-python
Project-URL: Repository, https://github.com/your-username/audiometa-python
Project-URL: Issues, https://github.com/your-username/audiometa-python/issues
Keywords: audio,metadata,mp3,flac,wav,id3,vorbis,riff
Classifier: Development Status :: 3 - Alpha
Classifier: Intended Audience :: Developers
Classifier: License :: OSI Approved :: Apache Software License
Classifier: Operating System :: OS Independent
Classifier: Programming Language :: Python :: 3
Classifier: Programming Language :: Python :: 3.12
Classifier: Programming Language :: Python :: 3.13
Classifier: Programming Language :: Python :: 3.14
Classifier: Topic :: Multimedia :: Sound/Audio
Classifier: Topic :: Software Development :: Libraries :: Python Modules
Requires-Python: >=3.12
License-File: LICENSE
Requires-Dist: mutagen==1.45.0
Provides-Extra: dev
Requires-Dist: pytest==9.0.1; extra == "dev"
Requires-Dist: pytest-cov==4.0.0; extra == "dev"
Requires-Dist: pytest-mock==3.15.1; extra == "dev"
Requires-Dist: ruff==0.6.9; extra == "dev"
Requires-Dist: isort==5.13.2; extra == "dev"
Requires-Dist: mypy==1.18.2; extra == "dev"
Requires-Dist: pre-commit==3.0.0; extra == "dev"
Requires-Dist: autoflake==2.0.0; extra == "dev"
Requires-Dist: pydocstringformatter==0.7.5; extra == "dev"
Requires-Dist: soundfile==0.10.1; extra == "dev"
Requires-Dist: numpy==2.3.4; extra == "dev"
Requires-Dist: bump2version==1.0.1; extra == "dev"
Provides-Extra: yaml
Requires-Dist: PyYAML==6.0; extra == "yaml"
Dynamic: license-file
